volcan/__init__.py
volcan/__main__.py
volcan/backend/__init__.py
volcan/frontend/__init__.py
volcan/frontend/lexer/__init__.py
volcan/frontend/lexer/keyword.py
volcan/frontend/lexer/lexer.py
volcan/frontend/lexer/symbol.py
volcan/frontend/lexer/token.py
volcan/frontend/parser/__init__.py
volcan-0.0.1.dist-info/WHEEL
volcan-0.0.1.dist-info/METADATA
volcan-0.0.1.dist-info/RECORD
