Metadata-Version: 2.1
Name: volcan
Version: 0.0.1
Summary: A modern, strongly-typed, general-purpose programming language.
License: MIT
Author: vcokltfre
Author-email: vcokltfre@gmail.com
Requires-Python: >=3.10,<4.0
Classifier: License :: OSI Approved :: MIT License
Classifier: Programming Language :: Python :: 3
Classifier: Programming Language :: Python :: 3.10
